intel_jtag_uart/__init__.py
intel_jtag_uart/intel_jtag_uart.py
intel_jtag_uart-0.0.3.dist-info/LICENSE
intel_jtag_uart-0.0.3.dist-info/METADATA
intel_jtag_uart-0.0.3.dist-info/WHEEL
intel_jtag_uart-0.0.3.dist-info/top_level.txt
intel_jtag_uart-0.0.3.dist-info/RECORD
