Metadata-Version: 2.1
Name: intel-jtag-uart
Version: 0.0.3
Summary: Package to interact with JTAG UART modules in Intel FPGA designs
Home-page: https://github.com/tomverbeure/intel_jtag_uart
Author: Tom Verbeure
Author-email: hombre@gmail.com
License: UNKNOWN
Project-URL: Bug Tracker, https://github.com/tomverbeure/intel_jtag_uart/issues
Platform: UNKNOWN
Classifier: Programming Language :: Python :: 3
Classifier: License :: OSI Approved :: MIT License
Classifier: Operating System :: OS Independent
Requires-Python: >=3.6
